simple_copoco/__init__.py
simple_copoco/config_handling.py
simple_copoco/objects_register.py
simple_copoco-0.2.2.dist-info/LICENSE
simple_copoco-0.2.2.dist-info/METADATA
simple_copoco-0.2.2.dist-info/WHEEL
simple_copoco-0.2.2.dist-info/RECORD
