Metadata-Version: 2.1
Name: simple-copoco
Version: 0.2.2
Summary: Effortlessly transition from YAML configuration to Python object management with the Simple Config Powered Code package.
Home-page: https://github.com/jakubgajski/simple_copoco
License: MIT
Keywords: configuration,dynamic code,experiments,yaml
Author: Jakub Gajski
Author-email: jakub.gajski@gmail.com
Requires-Python: >=3.10,<4.0
Classifier: License :: OSI Approved :: MIT License
Classifier: Programming Language :: Python :: 3
Classifier: Programming Language :: Python :: 3.10
Classifier: Programming Language :: Python :: 3.11
Classifier: Programming Language :: Python :: 3.12
Requires-Dist: multipledispatch (>=1.0.0,<2.0.0)
Requires-Dist: pyyaml (>=6.0.1,<7.0.0)
Project-URL: Repository, https://github.com/jakubgajski/simple_copoco
